attrs_patch/__init__.py
attrs_patch/attr/__init__.py
attrs_patch/attr/converters.py
attrs_patch/attr/validators.py
pedroasad_attrs_patch-0.2.1.dist-info/LICENSE.txt
pedroasad_attrs_patch-0.2.1.dist-info/WHEEL
pedroasad_attrs_patch-0.2.1.dist-info/METADATA
pedroasad_attrs_patch-0.2.1.dist-info/RECORD
