Metadata-Version: 2.1
Name: pedroasad-attrs-patch
Version: 0.2.1
Summary: A set of patches for the excellent attrs library
Home-page: https://psa-exe.gitlab.io/python-attrs-patch
License: MIT
Author: Pedro Asad
Author-email: pasad@lcg.ufrj.br
Requires-Python: >=3.5,<4.0
Classifier: License :: OSI Approved :: MIT License
Classifier: Programming Language :: Python :: 3
Classifier: Programming Language :: Python :: 3.5
Classifier: Programming Language :: Python :: 3.6
Classifier: Programming Language :: Python :: 3.7
Provides-Extra: all
Provides-Extra: numpy
Requires-Dist: attrs (>=19.1,<20.0)
Requires-Dist: numpy (>=1.16,<2.0); extra == "all" or extra == "numpy"
Project-URL: Documentation, https://psa-exe.gitlab.io/python-attrs-patch
Project-URL: Repository, https://gitlab.com/psa-exe/python-attrs-patch
